zengl_extras/__init__.py
zengl_extras/cudart.pyd
zengl_extras/opencl.pyd
zengl_extras-0.5.0.dist-info/LICENSE
zengl_extras-0.5.0.dist-info/METADATA
zengl_extras-0.5.0.dist-info/WHEEL
zengl_extras-0.5.0.dist-info/top_level.txt
zengl_extras-0.5.0.dist-info/RECORD
